MANIFEST.in
NEWS.txt
README.rst
setup.py
src/setuptools_clonedigger/__init__.py
src/setuptools_clonedigger/setuptools_command.py
src/setuptools_clonedigger.egg-info/PKG-INFO
src/setuptools_clonedigger.egg-info/SOURCES.txt
src/setuptools_clonedigger.egg-info/dependency_links.txt
src/setuptools_clonedigger.egg-info/entry_points.txt
src/setuptools_clonedigger.egg-info/not-zip-safe
src/setuptools_clonedigger.egg-info/requires.txt
src/setuptools_clonedigger.egg-info/top_level.txt