Metadata-Version: 1.0
Name: setuptools-clonedigger
Version: 0.1
Summary: Setuptools command for clonedigger
Home-page: https://github.com/johnnoone/setuptools-clonedigger
Author: Xavier Barbosa
Author-email: UNKNOWN
License: BSD
Keywords: clonedigger setuptools command
Platform: UNKNOWN
Classifier: Topic :: Documentation
Classifier: Framework :: Setuptools Plugin
Classifier: Development Status :: 4 - Beta
Classifier: Programming Language :: Python
Classifier: Intended Audience :: Developers
Classifier: Operating System :: OS Independent
Classifier: License :: OSI Approved :: BSD License
Classifier: Topic :: Software Development :: Documentation
Classifier: Topic :: Software Development :: Libraries :: Python Modules
